auterioncli/__init__.py
auterioncli/main.py
auterioncli/meta_util.py
auterioncli/commands/__init__.py
auterioncli/commands/app_command.py
auterioncli/commands/command_base.py
auterioncli/commands/container_command.py
auterioncli/commands/device_command.py
auterioncli/commands/info_command.py
auterioncli/commands/report_command.py
auterioncli/commands/utils.py
auterioncli/commands/app_sdk/__init__.py
auterioncli/commands/app_sdk/app_build_command.py
auterioncli/commands/app_sdk/app_init_command.py
auterioncli/commands/app_sdk/app_inspect_command.py
auterioncli/commands/app_sdk/app_install_command.py
auterioncli/commands/app_sdk/app_patch_command.py
auterioncli/commands/app_sdk/environment.py
auterioncli/commands/app_sdk/slimify.py
auterioncli/commands/app_sdk/update.py
auterioncli/commands/app_sdk/app-yml-spec/api-1.json
auterioncli/commands/app_sdk/app-yml-spec/api-2.json
auterioncli/commands/app_sdk/app-yml-spec/api-3-4.json
auterioncli/commands/app_sdk/app-yml-spec/api-5.json
auterioncli/commands/app_sdk/app-yml-spec/api-6.json
auterioncli/commands/app_sdk/app-yml-spec/api-7.json
auterioncli/commands/app_sdk/app-yml-spec/app-yml-spec.json
auterioncli/commands/app_sdk/app-yml-spec/compose-spec.json
auterion_cli-1.17.0.dist-info/METADATA
auterion_cli-1.17.0.dist-info/WHEEL
auterion_cli-1.17.0.dist-info/entry_points.txt
auterion_cli-1.17.0.dist-info/top_level.txt
auterion_cli-1.17.0.dist-info/RECORD
