Metadata-Version: 2.4
Name: auterion-cli
Version: 1.17.0
Summary: CLI tool to interact with AuterionOS devices and apps
Home-page: https://docs.auterion.com/app-development/resources/auterion-cli
Author: Auterion
Author-email: support@auterion.com
License: proprietary
Requires-Python: >=3.6
Requires-Dist: tabulate
Requires-Dist: requests
Requires-Dist: requests_toolbelt
Requires-Dist: zeroconf
Requires-Dist: websockets
Requires-Dist: packaging
Requires-Dist: tqdm
Requires-Dist: pyyaml
Requires-Dist: jsonschema
Requires-Dist: setuptools
Dynamic: author
Dynamic: author-email
Dynamic: home-page
Dynamic: license
Dynamic: requires-dist
Dynamic: requires-python
Dynamic: summary
